setup.py
django_memento.egg-info/PKG-INFO
django_memento.egg-info/SOURCES.txt
django_memento.egg-info/dependency_links.txt
django_memento.egg-info/top_level.txt
memento/__init__.py
memento/admin.py
memento/choices.py
memento/helpers.py
memento/models.py
memento/migrations/0001_initial.py
memento/migrations/0002_auto__del_event__add_logevent__chg_field_logentry_object_id__chg_field.py
memento/migrations/__init__.py
tests/__init__.py
tests/models.py
tests/settings.py
tests/tests.py
tests/urls.py