Metadata-Version: 1.0
Name: django-memento
Version: 0.1
Summary: Simple reusable django app for logging events within a django project
Home-page: http://relekang.github.io/django-memento
Author: Rolf Erik Lekang
Author-email: me@rolflekang.com
License: UNKNOWN
Platform: UNKNOWN
